infisical/__init__.py
infisical/__version__.py
infisical/constants.py
infisical/logger.py
infisical/api/__init__.py
infisical/api/create_secret.py
infisical/api/delete_secret.py
infisical/api/get_secret.py
infisical/api/get_secrets.py
infisical/api/get_service_token_data.py
infisical/api/get_service_token_data_key.py
infisical/api/models.py
infisical/api/update_secret.py
infisical/client/__init__.py
infisical/client/infisicalclient.py
infisical/exceptions/__init__.py
infisical/helpers/__init__.py
infisical/helpers/client.py
infisical/helpers/secrets.py
infisical/models/__init__.py
infisical/models/api.py
infisical/models/models.py
infisical/models/secret_service.py
infisical/services/__init__.py
infisical/services/secret_service.py
infisical/utils/__init__.py
infisical/utils/crypto.py
infisical/utils/http.py
infisical-1.5.0.dist-info/METADATA
infisical-1.5.0.dist-info/WHEEL
infisical-1.5.0.dist-info/licenses/LICENSE
infisical-1.5.0.dist-info/RECORD
