Metadata-Version: 2.1
Name: infisical
Version: 1.5.0
Summary: Official Infisical SDK for Python
Project-URL: Documentation, https://github.com/Infisical/infisical-python#readme
Project-URL: Issues, https://github.com/Infisical/infisical-python/issues
Project-URL: Source, https://github.com/Infisical/infisical-python
Maintainer-email: Yohann MARTIN <contact@codexus.fr>, Tony Dang <tony@infisical.com>
License-Expression: MIT
License-File: LICENSE
Classifier: Development Status :: 5 - Production/Stable
Classifier: Intended Audience :: Developers
Classifier: License :: OSI Approved :: MIT License
Classifier: Operating System :: OS Independent
Classifier: Programming Language :: Python
Classifier: Programming Language :: Python :: 3.7
Classifier: Programming Language :: Python :: 3.8
Classifier: Programming Language :: Python :: 3.9
Classifier: Programming Language :: Python :: 3.10
Classifier: Programming Language :: Python :: 3.11
Classifier: Programming Language :: Python :: Implementation :: CPython
Classifier: Programming Language :: Python :: Implementation :: PyPy
Classifier: Topic :: Software Development
Classifier: Topic :: Software Development :: Libraries
Classifier: Topic :: Software Development :: Libraries :: Application Frameworks
Classifier: Topic :: Software Development :: Libraries :: Python Modules
Classifier: Typing :: Typed
Requires-Python: >=3.7
Requires-Dist: pycryptodomex<4.0.0,>=3.17
Requires-Dist: pydantic!=1.7,!=1.7.1,!=1.7.2,!=1.7.3,!=1.8,!=1.8.1,<2.0.0,>=1.6.2
Requires-Dist: pynacl<2.0.0,>=1.5.0
Requires-Dist: requests==2.31.0
Provides-Extra: dev
Requires-Dist: black==23.3.0; extra == 'dev'
Requires-Dist: devtools[pygments]==0.11.0; extra == 'dev'
Requires-Dist: isort<6.0.0,>=5.0.6; extra == 'dev'
Requires-Dist: mypy==1.1.1; extra == 'dev'
Requires-Dist: ruff==0.0.261; extra == 'dev'
Requires-Dist: types-requests==2.28.11.17; extra == 'dev'
Provides-Extra: test
Requires-Dist: coverage[toml]<8.0,>=6.5.0; extra == 'test'
Requires-Dist: pytest<8.0.0,>=7.1.3; extra == 'test'
Requires-Dist: responses==0.23.1; extra == 'test'
